logmerger/__init__.py
logmerger/__main__.py
logmerger/about.py
logmerger/demo.py
logmerger/file_reading.py
logmerger/interactive_viewing.py
logmerger/logmerger.py
logmerger/merging.py
logmerger/multiline_log_handler.py
logmerger/timestamp_wrapper.py
logmerger/tui/__init__.py
logmerger/tui/dialogs.py
logmerger/tui/validators.py
logmerger-0.13.0.dist-info/licenses/LICENSE
logmerger-0.13.0.dist-info/METADATA
logmerger-0.13.0.dist-info/WHEEL
logmerger-0.13.0.dist-info/entry_points.txt
logmerger-0.13.0.dist-info/top_level.txt
logmerger-0.13.0.dist-info/RECORD
