Metadata-Version: 2.4
Name: logmerger
Version: 0.13.0
Summary: A command-line utility to display multiple log files, merged by log timestamp
Author-email: Paul McGuire <ptmcg.pm@gmail.com>
Maintainer-email: Paul McGuire <ptmcg.pm@gmail.com>
License-Expression: MIT
Project-URL: Source, https://github.com/ptmcg/logmerger
Keywords: logs,merge,timestamp,command-line,textual
Classifier: Development Status :: 4 - Beta
Classifier: Environment :: Console
Classifier: Intended Audience :: Developers
Classifier: Intended Audience :: Information Technology
Classifier: Intended Audience :: System Administrators
Classifier: Operating System :: OS Independent
Classifier: Programming Language :: Python :: 3
Classifier: Programming Language :: Python :: 3 :: Only
Classifier: Programming Language :: Python :: 3.10
Classifier: Programming Language :: Python :: 3.11
Classifier: Programming Language :: Python :: 3.12
Classifier: Programming Language :: Python :: 3.13
Classifier: Programming Language :: Python :: 3.14
Classifier: Topic :: System :: Systems Administration
Classifier: Topic :: Utilities
Classifier: Typing :: Typed
Requires-Python: >=3.10
License-File: LICENSE
Requires-Dist: littletable>=3.0.1
Requires-Dist: rich
Requires-Dist: typing-extensions>=4.12.0; python_version >= "3.13"
Requires-Dist: textual
Provides-Extra: pcap
Requires-Dist: pyshark; extra == "pcap"
Dynamic: license-file
